README.md
setup.py
gapcv/__init__.py
gapcv/vision.py
gapcv.egg-info/PKG-INFO
gapcv.egg-info/SOURCES.txt
gapcv.egg-info/dependency_links.txt
gapcv.egg-info/requires.txt
gapcv.egg-info/top_level.txt
gapcv/utils/__init__.py
gapcv/utils/img_tools.py